oslosphinx/__init__.py
oslosphinx/check_blueprints.py
oslosphinx/intersphinx.py
oslosphinx/theme/openstack/layout.html
oslosphinx/theme/openstack/theme.conf
oslosphinx/theme/openstack/static/basic.css
oslosphinx/theme/openstack/static/default.css
oslosphinx/theme/openstack/static/header-line.gif
oslosphinx/theme/openstack/static/header_bg.jpg
oslosphinx/theme/openstack/static/nature.css
oslosphinx/theme/openstack/static/openstack_logo.png
oslosphinx/theme/openstack/static/tweaks.css
oslosphinx-4.18.0.dist-info/DESCRIPTION.rst
oslosphinx-4.18.0.dist-info/METADATA
oslosphinx-4.18.0.dist-info/RECORD
oslosphinx-4.18.0.dist-info/WHEEL
oslosphinx-4.18.0.dist-info/metadata.json
oslosphinx-4.18.0.dist-info/pbr.json
oslosphinx-4.18.0.dist-info/top_level.txt
